Verilog Code/GELU.v
module Gelu #(parameter in_width=10,dataWidth=32)(
    input [in_width-1:0]in,
    input clk,
    output [dataWidth-1:0]out
);

// Memory Block;
reg [dataWidth-1:0]mem[0:2**in_width-1];
reg [in_width-1 : 0 ]y;

// initializing the .mif file;
initial begin 
    $readmemb("float32_output.csv",mem);
end 

always @(posedge clk)
    begin
        if($signed(in) >= 0)// if input x is positive no.
            y <= in+(2**(in_width-1));
        else 
            y <= in-(2**(in_width-1));   // if input x is negative.  
    end

assign out = mem[y];
endmodule

Verilog Code/GELU_testbench.v
// Testbench for GELU module
`timescale 1ps/1ps
module tb_gelu;

    // Parameters
    localparam in_width  = 10;
    localparam dataWidth = 32;

    // Clock and signals
    reg                         clk;
    reg  [in_width-1:0]         in;
    wire [dataWidth-1:0]        out;

    // Reference memory (same as DUT)
    reg [dataWidth-1:0]         ref_mem [0:(1<<in_width)-1];

    // Instantiate DUT
    Gelu #(
        .in_width (in_width),
        .dataWidth(dataWidth)
    ) u_gelu (
        .in  (in),
        .clk (clk),
        .out (out)
    );

    // Clock generation (10 ns period)
    always #5 clk = ~clk;

    // Load the MIF file into reference memory
    initial begin
        $readmemb("float32_output.csv", ref_mem);
    end

    // Main test procedure
    integer i;
    reg [in_width-1:0] y;          // computed address
    reg [dataWidth-1:0] expected;

    initial begin 
        $dumpfile("testbench.vcd");
        $dumpvars(0,tb_gelu);
    end

    initial begin
        // Initialize signals
        clk = 0;
        in  = 0;

        // Apply reset (optional – not used by DUT, but good practice)
        repeat (2) @(posedge clk);

        // Loop over all possible signed 10-bit inputs
        for (i = -512; i <= 511; i = i + 1) begin
            // Convert integer to 10-bit signed representation
            in = i[in_width-1:0];    // truncate to 10 bits (preserves sign)

            // Wait one clock cycle for the output to update (DUT has one cycle latency)
            @(posedge clk);

            // Compute the address that DUT would use (same logic as in DUT)
            if ($signed(in) >= 0)
                y = in + (1 << (in_width-1));
            else
                y = in - (1 << (in_width-1));

            // Fetch expected value from reference memory
            expected = ref_mem[y];

            // Compare with DUT output
            if (out === expected) begin
                $display("[PASS] in = %0d (0x%0h) -> y = 0x%0h, out = 0x%0h", 
                         $signed(in), in, y, out);
            end else begin
                $display("[FAIL] in = %0d (0x%0h) -> y = 0x%0h, out = 0x%0h, expected = 0x%0h",
                         $signed(in), in, y, out, expected);
            end
        end

        $display("Test completed.");
        $finish;
    end

endmodule

Verilog Code/testbench.vcd
$date
	Tue May 26 19:42:08 2026
$end
$version
	Icarus Verilog
$end
$timescale
	1ps
$end
$scope module tb_gelu $end
$var wire 32 ! out [31:0] $end
$var parameter 32 " dataWidth $end
$var parameter 32 # in_width $end
$var reg 1 $ clk $end
$var reg 32 % expected [31:0] $end
$var reg 10 & in [9:0] $end
$var reg 10 ' y [9:0] $end
$var integer 32 ( i [31:0] $end
$scope module u_gelu $end
$var wire 1 $ clk $end
$var wire 10 ) in [9:0] $end
$var wire 32 * out [31:0] $end
$var parameter 32 + dataWidth $end
$var parameter 32 , in_width $end
$var reg 10 - y [9:0] $end
$upscope $end
$upscope $end
$enddefinitions $end
$comment Show the parameter values. $end
$dumpall
b1010 ,
b100000 +
b1010 #
b100000 "
$end
#0
$dumpvars
bx -
bx *
b0 )
bx (
bx '
b0 &
bx %
0$
bx !
$end
#5
b111011010000010001011001001001 !
b111011010000010001011001001001 *
b1000000000 -
1$
#10
0$
#15
b1000000000 &
b1000000000 )
b11111111111111111111111000000000 (
1$
#20
0$
#25
b10110001110110100011000000101110 !
b10110001110110100011000000101110 *
b1 -
b1000000001 &
b1000000001 )
b11111111111111111111111000000001 (
b10110001110010110110010010110011 %
b0 '
1$
#30
0$
#35
b1000000010 &
b1000000010 )
b11111111111111111111111000000010 (
b10110001110110100011000000101110 %
b1 '
1$
#40
0$
#45
b10110001111110101111101100001110 !
b10110001111110101111101100001110 *
b11 -
b1000000011 &
b1000000011 )
b11111111111111111111111000000011 (
b10110001111010100000011011100011 %
b10 '
1$
#50
0$
#55
b1000000100 &
b1000000100 )
b11111111111111111111111000000100 (
b10110001111110101111101100001110 %
b11 '
1$
#60
0$
#65
b10110010000100000100010101100111 !
b10110010000100000100010101100111 *
b101 -
b1000000101 &
b1000000101 )
b11111111111111111111111000000101 (
b10110010000001101001000000010000 %
b100 '
1$
#70
0$
#75
b1000000110 &
b1000000110 )
b11111111111111111111111000000110 (
b10110010000100000100010101100111 %
b101 '
1$
#80
0$
#85
b10110010001001011100010101011110 !
b10110010001001011100010101011110 *
b111 -
b1000000111 &
b1000000111 )
b11111111111111111111111000000111 (
b10110010000110101010100010010111 %
b110 '
1$
#90
0$
#95
b1000001000 &
b1000001000 )
b11111111111111111111111000001000 (
b10110010001001011100010101011110 %
b111 '
1$
#100
0$
#105
b10110010001111100101111010011110 !
b10110010001111100101111010011110 *
b1001 -
b1000001001 &
b1000001001 )
b11111111111111111111111000001001 (
b10110010001100011010100001000100 %
b1000 '
1$
#110
0$
#115
b1000001010 &
b1000001010 )
b11111111111111111111111000001010 (
b10110010001111100101111010011110 %
b1001 '
1$
#120
0$
#125
b10110010010110100111111101100100 !
b10110010010110100111111101100100 *
b1011 -
b1000001011 &
b1000001011 )
b11111111111111111111111000001011 (
b10110010010010111111011010011111 %
b1010 '
1$
#130
0$
#135
b1000001100 &
b1000001100 )
b11111111111111111111111000001100 (
b10110010010110100111111101100100 %
b1011 '
1$
#140
0$
#145
b10110010011110101010010010100101 !
b10110010011110101010010010100101 *
b1101 -
b1000001101 &
b1000001101 )
b11111111111111111111111000001101 (
b10110010011010100000100100000110 %
b1100 '
1$
#150
0$
#155
b1000001110 &
b1000001110 )
b11111111111111111111111000001110 (
b10110010011110101010010010100101 %
b1101 '
1$
#160
0$
#165
b10110010100011111010110111110110 !
b10110010100011111010110111110110 *
b1111 -
b1000001111 &
b1000001111 )
b11111111111111111111111000001111 (
b10110010100001100011001000111101 %
b1110 '
1$
#170
0$
#175
b1000010000 &
b1000010000 )
b11111111111111111111111000010000 (
b10110010100011111010110111110110 %
b1111 '
1$
#180
0$
#185
b10110010101001001010001010111100 !
b10110010101001001010001010111100 *
b10001 -
b1000010001 &
b1000010001 )
b11111111111111111111111000010001 (
b10110010100110011100111111001101 %
b10000 '
1$
#190
0$
#195
b1000010010 &
b1000010010 )
b11111111111111111111111000010010 (
b10110010101001001010001010111100 %
b10001 '
1$
#200
0$
#205
b10110010101111001000101101001010 !
b10110010101111001000101101001010 *
b10011 -
b1000010011 &
b1000010011 )
b11111111111111111111111000010011 (
b10110010101100000011001001101101 %
b10010 '
1$
#210
0$
#215
b1000010100 &
b1000010100 )
b11111111111111111111111000010100 (
b10110010101111001000101101001010 %
b10011 '
1$
#220
0$
#225
b10110010110101111100111000100000 !
b10110010110101111100111000100000 *
b10101 -
b1000010101 &
b1000010101 )
b11111111111111111111111000010101 (
b10110010110010011011101010000011 %
b10100 '
1$
#230
0$
#235
b1000010110 &
b1000010110 )
b11111111111111111111111000010110 (
b10110010110101111100111000100000 %
b10101 '
1$
#240
0$
#245
b10110010111101101101111100010000 !
b10110010111101101101111100010000 *
b10111 -
b1000010111 &
b1000010111 )
b11111111111111111111111000010111 (
b10110010111001101101010100000111 %
b10110 '
1$
#250
0$
#255
b1000011000 &
b1000011000 )
b11111111111111111111111000011000 (
b10110010111101101101111100010000 %
b10111 '
1$
#260
0$
#265
b10110011000011010010000001110100 !
b10110011000011010010000001110100 *
b11001 -
b1000011001 &
b1000011001 )
b11111111111111111111111000011001 (
b10110011000000111111111010001000 %
b11000 '
1$
#270
0$
#275
b1000011010 &
b1000011010 )
b11111111111111111111111000011010 (
b10110011000011010010000001110100 %
b11001 '
1$
#280
0$
#285
b10110011001000010100001110100011 !
b10110011001000010100001110100011 *
b11011 -
b1000011011 &
b1000011011 )
b11111111111111111111111000011011 (
b10110011000101101101111011001011 %
b11010 '
1$
#290
0$
#295
b1000011100 &
b1000011100 )
b11111111111111111111111000011100 (
b10110011001000010100001110100011 %
b11011 '
1$
#300
0$
#305
b10110011001110000010110001011000 !
b10110011001110000010110001011000 *
b11101 -
b1000011101 &
b1000011101 )
b11111111111111111111111000011101 (
b10110011001011000101100110110011 %
b11100 '
1$
#310
0$
#315
b1000011110 &
b1000011110 )
b11111111111111111111111000011110 (
b10110011001110000010110001011000 %
b11101 '
1$
#320
0$
#325
b10110011010100100011100001101010 !
b10110011010100100011100001101010 *
b11111 -
b1000011111 &
b1000011111 )
b11111111111111111111111000011111 (
b10110011010001001100011110100101 %
b11110 '
1$
#330
0$
#335
b1000100000 &
b1000100000 )
b11111111111111111111111000100000 (
b10110011010100100011100001101010 %
b11111 '
1$
#340
0$
#345
b10110011011011111101000110010010 !
b10110011011011111101000110010010 *
b100001 -
b1000100001 &
b1000100001 )
b11111111111111111111111000100001 (
b10110011011000001000110000111111 %
b100000 '
1$
#350
0$
#355
b1000100010 &
b1000100010 )
b11111111111111111111111000100010 (
b10110011011011111101000110010010 %
b100001 '
1$
#360
0$
#365
b10110011100010001011011101101100 !
b10110011100010001011011101101100 *
b100011 -
b1000100011 &
b1000100011 )
b11111111111111111111111000100011 (
b10110011100000000000101111011001 %
b100010 '
1$
#370
0$
#375
b1000100100 &
b1000100100 )
b11111111111111111111111000100100 (
b10110011100010001011011101101100 %
b100011 '
1$
#380
0$
#385
b10110011100110111100101100010011 !
b10110011100110111100101100010011 *
b100101 -
b1000100101 &
b1000100101 )
b11111111111111111111111000100101 (
b10110011100100011111010000011111 %
b100100 '
1$
#390
0$
#395
b1000100110 &
b1000100110 )
b11111111111111111111111000100110 (
b10110011100110111100101100010011 %
b100101 '
1$
#400
0$
#405
b10110011101100010110111100001001 !
b10110011101100010110111100001001 *
b100111 -
b1000100111 &
b1000100111 )
b11111111111111111111111000100111 (
b10110011101001100100010111110101 %
b100110 '
1$
#410
0$
#415
b1000101000 &
b1000101000 )
b11111111111111111111111000101000 (
b10110011101100010110111100001001 %
b100111 '
1$
#420
0$
#425
b10110011110010011111011111101011 !
b10110011110010011111011111101011 *
b101001 -
b1000101001 &
b1000101001 )
b11111111111111111111111000101001 (
b10110011101111010101000100101110 %
b101000 '
1$
#430
0$
#435
b1000101010 &
b1000101010 )
b11111111111111111111111000101010 (
b10110011110010011111011111101011 %
b101001 '
1$
#440
0$
#445
b10110011111001011100010010111110 !
b10110011111001011100010010111110 *
b101011 -
b1000101011 &
b1000101011 )
b11111111111111111111111000101011 (
b10110011110101110110111101110110 %
b101010 '
1$
#450
0$
#455
b1000101100 &
b1000101100 )
b11111111111111111111111000101100 (
b10110011111001011100010010111110 %
b101011 '
1$
#460
0$
#465
b10110100000000101010000000010100 !
b10110100000000101010000000010100 *
b101101 -
b1000101101 &
b1000101101 )
b11111111111111111111111000101101 (
b10110011111101010000010101111000 %
b101100 '
1$
#470
0$
#475
b1000101110 &
b1000101110 )
b11111111111111111111111000101110 (
b10110100000000101010000000010100 %
b101101 '
1$
#480
0$
#485
b10110100000101000111000011100011 !
b10110100000101000111000011100011 *
b101111 -
b1000101111 &
b1000101111 )
b11111111111111111111111000101111 (
b10110100000010110100001000010101 %
b101110 '
1$
#490
0$
#495
b1000110000 &
b1000110000 )
b11111111111111111111111000110000 (
b10110100000101000111000011100011 %
b101111 '
1$
#500
0$
#505
b10110100001010001001011111011000 !
b10110100001010001001011111011000 *
b110001 -
b1000110001 &
b1000110001 )
b11111111111111111111111000110001 (
b10110100000111100011010100011010 %
b110000 '
1$
#510
0$
#515
b1000110010 &
b1000110010 )
b11111111111111111111111000110010 (
b10110100001010001001011111011000 %
b110001 '
1$
#520
0$
#525
b10110100001111110110000000001111 !
b10110100001111110110000000001111 *
b110011 -
b1000110011 &
b1000110011 )
b11111111111111111111111000110011 (
b10110100001100111010001011000011 %
b110010 '
1$
#530
0$
#535
b1000110100 &
b1000110100 )
b11111111111111111111111000110100 (
b10110100001111110110000000001111 %
b110011 '
1$
#540
0$
#545
b10110100010110010001110110011101 !
b10110100010110010001110110011101 *
b110101 -
b1000110101 &
b1000110101 )
b11111111111111111111111000110101 (
b10110100010010111101101010001001 %
b110100 '
1$
#550
0$
#555
b1000110110 &
b1000110110 )
b11111111111111111111111000110110 (
b10110100010110010001110110011101 %
b110101 '
1$
#560
0$
#565
b10110100011101100010111010010110 !
b10110100011101100010111010010110 *
b110111 -
b1000110111 &
b1000110111 )
b11111111111111111111111000110111 (
b10110100011001110011010101011111 %
b110110 '
1$
#570
0$
#575
b1000111000 &
b1000111000 )
b11111111111111111111111000111000 (
b10110100011101100010111010010110 %
b110111 '
1$
#580
0$
#585
b10110100100010110111111000010110 !
b10110100100010110111111000010110 *
b111001 -
b1000111001 &
b1000111001 )
b11111111111111111111111000111001 (
b10110100100000110000101101100001 %
b111000 '
1$
#590
0$
#595
b1000111010 &
b1000111010 )
b11111111111111111111111000111010 (
b10110100100010110111111000010110 %
b111001 '
1$
#600
0$
#605
b10110100100111011111110111110110 !
b10110100100111011111110111110110 *
b111011 -
b1000111011 &
b1000111011 )
b11111111111111111111111000111011 (
b10110100100101000111011011110101 %
b111010 '
1$
#610
0$
#615
b1000111100 &
b1000111100 )
b11111111111111111111111000111100 (
b10110100100111011111110111110110 %
b111011 '
1$
#620
0$
#625
b10110100101100101101100010001101 !
b10110100101100101101100010001101 *
b111101 -
b1000111101 &
b1000111101 )
b11111111111111111111111000111101 (
b10110100101010000001101110000111 %
b111100 '
1$
#630
0$
#635
b1000111110 &
b1000111110 )
b11111111111111111111111000111110 (
b10110100101100101101100010001101 %
b111101 '
1$
#640
0$
#645
b10110100110010100101011100011101 !
b10110100110010100101011100011101 *
b111111 -
b1000111111 &
b1000111111 )
b11111111111111111111111000111111 (
b10110100101111100011111001110000 %
b111110 '
1$
#650
0$
#655
b1001000000 &
b1001000000 )
b11111111111111111111111001000000 (
b10110100110010100101011100011101 %
b111111 '
1$
#660
0$
#665
b10110100111001001100101101011000 !
b10110100111001001100101101011000 *
b1000001 -
b1001000001 &
b1001000001 )
b11111111111111111111111001000001 (
b10110100110101110010110100001111 %
b1000000 '
1$
#670
0$
#675
b1001000010 &
b1001000010 )
b11111111111111111111111001000010 (
b10110100111001001100101101011000 %
b1000001 '
1$
#680
0$
#685
b10110101000000010100100000101000 !
b10110101000000010100100000101000 *
b1000011 -
b1001000011 &
b1001000011 )
b11111111111111111111111001000011 (
b10110100111100110011110110100110 %
b1000010 '
1$
#690
0$
#695
b1001000100 &
b1001000100 )
b11111111111111111111111001000100 (
b10110101000000010100100000101000 %
b1000011 '
1$
#700
0$
#705
b10110101000100100000010110111010 !
b10110101000100100000010110111010 *
b1000101 -
b1001000101 &
b1001000101 )
b11111111111111111111111001000101 (
b10110101000010010110100000101011 %
b1000100 '
1$
#710
0$
#715
b1001000110 &
b1001000110 )
b11111111111111111111111001000110 (
b10110101000100100000010110111010 %
b1000101 '
1$
#720
0$
#725
b10110101001001001101011011011001 !
b10110101001001001101011011011001 *
b1000111 -
b1001000111 &
b1001000111 )
b11111111111111111111111001000111 (
b10110101000110110010100000010011 %
b1000110 '
1$
#730
0$
#735
b1001001000 &
b1001001000 )
b11111111111111111111111001001000 (
b10110101001001001101011011011001 %
b1000111 '
1$
#740
0$
#745
b10110101001110011111101001010111 !
b10110101001110011111101001010111 *
b1001001 -
b1001001001 &
b1001001001 )
b11111111111111111111111001001001 (
b10110101001011110001101000011011 %
b1001000 '
1$
#750
0$
#755
b1001001010 &
b1001001010 )
b11111111111111111111111001001010 (
b10110101001110011111101001010111 %
b1001001 '
1$
#760
0$
#765
b10110101010100011011011000001001 !
b10110101010100011011011000001001 *
b1001011 -
b1001001011 &
b1001001011 )
b11111111111111111111111001001011 (
b10110101010001011000000010000000 %
b1001010 '
1$
#770
0$
#775
b1001001100 &
b1001001100 )
b11111111111111111111111001001100 (
b10110101010100011011011000001001 %
b1001011 '
1$
#780
0$
#785
b10110101011011000101011110001001 !
b10110101011011000101011110001001 *
b1001101 -
b1001001101 &
b1001001101 )
b11111111111111111111111001001101 (
b10110101010111101010010011100010 %
b1001100 '
1$
#790
0$
#795
b1001001110 &
b1001001110 )
b11111111111111111111111001001110 (
b10110101011011000101011110001001 %
b1001101 '
1$
#800
0$
#805
b10110101100001010001101010000000 !
b10110101100001010001101010000000 *
b1001111 -
b1001001111 &
b1001001111 )
b11111111111111111111111001001111 (
b10110101011110101101100100000111 %
b1001110 '
1$
#810
0$
#815
b1001010000 &
b1001010000 )
b11111111111111111111111001010000 (
b10110101100001010001101010000000 %
b1001111 '
1$
#820
0$
#825
b10110101100101011101011100000111 !
b10110101100101011101011100000111 *
b1010001 -
b1001010001 &
b1001010001 )
b11111111111111111111111001010001 (
b10110101100011010011101111011011 %
b1010000 '
1$
#830
0$
#835
b1001010010 &
b1001010010 )
b11111111111111111111111001010010 (
b10110101100101011101011100000111 %
b1010001 '
1$
#840
0$
#845
b10110101101010001001011001011100 !
b10110101101010001001011001011100 *
b1010011 -
b1001010011 &
b1001010011 )
b11111111111111111111111001010011 (
b10110101100111101111001011010000 %
b1010010 '
1$
#850
0$
#855
b1001010100 &
b1001010100 )
b11111111111111111111111001010100 (
b10110101101010001001011001011100 %
b1010011 '
1$
#860
0$
#865
b10110101101111011001001101000010 !
b10110101101111011001001101000010 *
b1010101 -
b1001010101 &
b1001010101 )
b11111111111111111111111001010101 (
b10110101101100101100100100110011 %
b1010100 '
1$
#870
0$
#875
b1001010110 &
b1001010110 )
b11111111111111111111111001010110 (
b10110101101111011001001101000010 %
b1010101 '
1$
#880
0$
#885
b10110101110101010000111011001011 !
b10110101110101010000111011001011 *
b1010111 -
b1001010111 &
b1001010111 )
b11111111111111111111111001010111 (
b10110101110010001111110011011101 %
b1010110 '
1$
#890
0$
#895
b1001011000 &
b1001011000 )
b11111111111111111111111001011000 (
b10110101110101010000111011001011 %
b1010111 '
1$
#900
0$
#905
b10110101111011110101000011111110 !
b10110101111011110101000011111110 *
b1011001 -
b1001011001 &
b1001011001 )
b11111111111111111111111001011001 (
b10110101111000011101001001000101 %
b1011000 '
1$
#910
0$
#915
b1001011010 &
b1001011010 )
b11111111111111111111111001011010 (
b10110101111011110101000011111110 %
b1011001 '
1$
#920
0$
#925
b10110110000001100101010011000100 !
b10110110000001100101010011000100 *
b1011011 -
b1001011011 &
b1001011011 )
b11111111111111111111111001011011 (
b10110101111111011001010100101100 %
b1011010 '
1$
#930
0$
#935
b1001011100 &
b1001011100 )
b11111111111111111111111001011100 (
b10110110000001100101010011000100 %
b1011011 '
1$
#940
0$
#945
b10110110000101101011100000111101 !
b10110110000101101011100000111101 *
b1011101 -
b1001011101 &
b1001011101 )
b11111111111111111111111001011101 (
b10110110000011100100110010101101 %
b1011100 '
1$
#950
0$
#955
b1001011110 &
b1001011110 )
b11111111111111111111111001011110 (
b10110110000101101011100000111101 %
b1011101 '
1$
#960
0$
#965
b10110110001010010000001110001110 !
b10110110001010010000001110001110 *
b1011111 -
b1001011111 &
b1001011111 )
b11111111111111111111111001011111 (
b10110110000111111001110110101111 %
b1011110 '
1$
#970
0$
#975
b1001100000 &
b1001100000 )
b11111111111111111111111001100000 (
b10110110001010010000001110001110 %
b1011111 '
1$
#980
0$
#985
b10110110001111010110110001101100 !
b10110110001111010110110001101100 *
b1100001 -
b1001100001 &
b1001100001 )
b11111111111111111111111001100001 (
b10110110001100101111000010111011 %
b1100000 '
1$
#990
0$
#995
b1001100010 &
b1001100010 )
b11111111111111111111111001100010 (
b10110110001111010110110001101100 %
b1100001 '
1$
#1000
0$
#1005
b10110110010101000010111000010101 !
b10110110010101000010111000010101 *
b1100011 -
b1001100011 &
b1001100011 )
b11111111111111111111111001100011 (
b10110110010010000111111000111000 %
b1100010 '
1$
#1010
0$
#1015
b1001100100 &
b1001100100 )
b11111111111111111111111001100100 (
b10110110010101000010111000010101 %
b1100011 '
1$
#1020
0$
#1025
b10110110011011011000100111011100 !
b10110110011011011000100111011100 *
b1100101 -
b1001100101 &
b1001100101 )
b11111111111111111111111001100101 (
b10110110011000001000010001011111 %
b1100100 '
1$
#1030
0$
#1035
b1001100110 &
b1001100110 )
b11111111111111111111111001100110 (
b10110110011011011000100111011100 %
b1100101 '
1$
#1040
0$
#1045
b10110110100001001110001111011100 !
b10110110100001001110001111011100 *
b1100111 -
b1001100111 &
b1001100111 )
b11111111111111111111111001100111 (
b10110110011110110100011111000001 %
b1100110 '
1$
#1050
0$
#1055
b1001101000 &
b1001101000 )
b11111111111111111111111001101000 (
b10110110100001001110001111011100 %
b1100111 '
1$
#1060
0$
#1065
b10110110100101001001101101110110 !
b10110110100101001001101101110110 *
b1101001 -
b1001101001 &
b1001101001 )
b11111111111111111111111001101001 (
b10110110100011001000100111110011 %
b1101000 '
1$
#1070
0$
#1075
b1001101010 &
b1001101010 )
b11111111111111111111111001101010 (
b10110110100101001001101101110110 %
b1101001 '
1$
#1080
0$
#1085
b10110110101001100001011101010100 !
b10110110101001100001011101010100 *
b1101011 -
b1001101011 &
b1001101011 )
b11111111111111111111111001101011 (
b10110110100111010001110111111000 %
b1101010 '
1$
#1090
0$
#1095
b1001101100 &
b1001101100 )
b11111111111111111111111001101100 (
b10110110101001100001011101010100 %
b1101011 '
1$
#1100
0$
#1105
b10110110101110011000011101101001 !
b10110110101110011000011101101001 *
b1101101 -
b1001101101 &
b1001101101 )
b11111111111111111111111001101101 (
b10110110101011111000110110101010 %
b1101100 '
1$
#1110
0$
#1115
b1001101110 &
b1001101110 )
b11111111111111111111111001101110 (
b10110110101110011000011101101001 %
b1101101 '
1$
#1120
0$
#1125
b10110110110011110010000001100101 !
b10110110110011110010000001100101 *
b1101111 -
b1001101111 &
b1001101111 )
b11111111111111111111111001101111 (
b10110110110001000000101101001100 %
b1101110 '
1$
#1130
0$
#1135
b1001110000 &
b1001110000 )
b11111111111111111111111001110000 (
b10110110110011110010000001100101 %
b1101111 '
1$
#1140
0$
#1145
b10110110111001110001110000100101 !
b10110110111001110001110000100101 *
b1110001 -
b1001110001 &
b1001110001 )
b11111111111111111111111001110001 (
b10110110110110101100111000011000 %
b1110000 '
1$
#1150
0$
#1155
b1001110010 &
b1001110010 )
b11111111111111111111111001110010 (
b10110110111001110001110000100101 %
b1110001 '
1$
#1160
0$
#1165
b10110111000000001101110100010101 !
b10110111000000001101110100010101 *
b1110011 -
b1001110011 &
b1001110011 )
b11111111111111111111111001110011 (
b10110110111101000001001010101011 %
b1110010 '
1$
#1170
0$
#1175
b1001110100 &
b1001110100 )
b11111111111111111111111001110100 (
b10110111000000001101110100010101 %
b1110011 '
1$
#1180
0$
#1185
b10110111000011111010000000001100 !
b10110111000011111010000000001100 *
b1110101 -
b1001110101 &
b1001110101 )
b11111111111111111111111001110101 (
b10110111000010000000110111000100 %
b1110100 '
1$
#1190
0$
#1195
b1001110110 &
b1001110110 )
b11111111111111111111111001110110 (
b10110111000011111010000000001100 %
b1110101 '
1$
#1200
0$
#1205
b10110111000111111111110100100011 !
b10110111000111111111110100100011 *
b1110111 -
b1001110111 &
b1001110111 )
b11111111111111111111111001110111 (
b10110111000101111001100011001101 %
b1110110 '
1$
#1210
0$
#1215
b1001111000 &
b1001111000 )
b11111111111111111111111001111000 (
b10110111000111111111110100100011 %
b1110111 '
1$
#1220
0$
#1225
b10110111001100100001111000100111 !
b10110111001100100001111000100111 *
b1111001 -
b1001111001 &
b1001111001 )
b11111111111111111111111001111001 (
b10110111001010001101001001100100 %
b1111000 '
1$
#1230
0$
#1235
b1001111010 &
b1001111010 )
b11111111111111111111111001111010 (
b10110111001100100001111000100111 %
b1111001 '
1$
#1240
0$
#1245
b10110111010001100011000011011001 !
b10110111010001100011000011011001 *
b1111011 -
b1001111011 &
b1001111011 )
b11111111111111111111111001111011 (
b10110111001110111110011001000100 %
b1111010 '
1$
#1250
0$
#1255
b1001111100 &
b1001111100 )
b11111111111111111111111001111100 (
b10110111010001100011000011011001 %
b1111011 '
1$
#1260
0$
#1265
b10110111010111000110011101000110 !
b10110111010111000110011101000110 *
b1111101 -
b1001111101 &
b1001111101 )
b11111111111111111111111001111101 (
b10110111010100010000010001001010 %
b1111100 '
1$
#1270
0$
#1275
b1001111110 &
b1001111110 )
b11111111111111111111111001111110 (
b10110111010111000110011101000110 %
b1111101 '
1$
#1280
0$
#1285
b10110111011101001111100000100011 !
b10110111011101001111100000100011 *
b1111111 -
b1001111111 &
b1001111111 )
b11111111111111111111111001111111 (
b10110111011010000110000011001010 %
b1111110 '
1$
#1290
0$
#1295
b1010000000 &
b1010000000 )
b11111111111111111111111010000000 (
b10110111011101001111100000100011 %
b1111111 '
1$
#1300
0$
#1305
b10110111100010000000111110011001 !
b10110111100010000000111110011001 *
b10000001 -
b1010000001 &
b1010000001 )
b11111111111111111111111010000001 (
b10110111100000010001101001111001 %
b10000000 '
1$
#1310
0$
#1315
b1010000010 &
b1010000010 )
b11111111111111111111111010000010 (
b10110111100010000000111110011001 %
b10000001 '
1$
#1320
0$
#1325
b10110111100101110000111011010110 !
b10110111100101110000111011010110 *
b10000011 -
b1010000011 &
b1010000011 )
b11111111111111111111111010000011 (
b10110111100011110101111110011010 %
b10000010 '
1$
#1330
0$
#1335
b1010000100 &
b1010000100 )
b11111111111111111111111010000100 (
b10110111100101110000111011010110 %
b10000011 '
1$
#1340
0$
#1345
b10110111101001111001110101011110 !
b10110111101001111001110101011110 *
b10000101 -
b1010000101 &
b1010000101 )
b11111111111111111111111010000101 (
b10110111100111110010000111011000 %
b10000100 '
1$
#1350
0$
#1355
b1010000110 &
b1010000110 )
b11111111111111111111111010000110 (
b10110111101001111001110101011110 %
b10000101 '
1$
#1360
0$
#1365
b10110111101110011110000111111010 !
b10110111101110011110000111111010 *
b10000111 -
b1010000111 &
b1010000111 )
b11111111111111111111111010000111 (
b10110111101100001000011001011011 %
b10000110 '
1$
#1370
0$
#1375
b1010001000 &
b1010001000 )
b11111111111111111111111010001000 (
b10110111101110011110000111111010 %
b10000111 '
1$
#1380
0$
#1385
b10110111110011100000011011101010 !
b10110111110011100000011011101010 *
b10001001 -
b1010001001 &
b1010001001 )
b11111111111111111111111010001001 (
b10110111110000111011010110011111 %
b10001000 '
1$
#1390
0$
#1395
b1010001010 &
b1010001010 )
b11111111111111111111111010001010 (
b10110111110011100000011011101010 %
b10001001 '
1$
#1400
0$
#1405
b10110111111001000011101000101111 !
b10110111111001000011101000101111 *
b10001011 -
b1010001011 &
b1010001011 )
b11111111111111111111111010001011 (
b10110111110110001101101110111011 %
b10001010 '
1$
#1410
0$
#1415
b1010001100 &
b1010001100 )
b11111111111111111111111010001100 (
b10110111111001000011101000101111 %
b10001011 '
1$
#1420
0$
#1425
b10110111111111001010110111010000 !
b10110111111111001010110111010000 *
b10001101 -
b1010001101 &
b1010001101 )
b11111111111111111111111010001101 (
b10110111111100000010100010101000 %
b10001100 '
1$
#1430
0$
#1435
b1010001110 &
b1010001110 )
b11111111111111111111111010001110 (
b10110111111111001010110111010000 %
b10001101 '
1$
#1440
0$
#1445
b10111000000010111100110000011011 !
b10111000000010111100110000011011 *
b10001111 -
b1010001111 &
b1010001111 )
b11111111111111111111111010001111 (
b10111000000001001110100001001011 %
b10001110 '
1$
#1450
0$
#1455
b1010010000 &
b1010010000 )
b11111111111111111111111010010000 (
b10111000000010111100110000011011 %
b10001111 '
1$
#1460
0$
#1465
b10111000000110101001101000111100 !
b10111000000110101001101000111100 *
b10010001 -
b1010010001 &
b1010010001 )
b11111111111111111111111010010001 (
b10111000000100110000011000011100 %
b10010000 '
1$
#1470
0$
#1475
b1010010010 &
b1010010010 )
b11111111111111111111111010010010 (
b10111000000110101001101000111100 %
b10010001 '
1$
#1480
0$
#1485
b10111000001010101110000101100001 !
b10111000001010101110000101100001 *
b10010011 -
b1010010011 &
b1010010011 )
b11111111111111111111111010010011 (
b10111000001000101000110010010010 %
b10010010 '
1$
#1490
0$
#1495
b1010010100 &
b1010010100 )
b11111111111111111111111010010100 (
b10111000001010101110000101100001 %
b10010011 '
1$
#1500
0$
#1505
b10111000001111001100010001010101 !
b10111000001111001100010001010101 *
b10010101 -
b1010010101 &
b1010010101 )
b11111111111111111111111010010101 (
b10111000001100111001110100010111 %
b10010100 '
1$
#1510
0$
#1515
b1010010110 &
b1010010110 )
b11111111111111111111111010010110 (
b10111000001111001100010001010101 %
b10010101 '
1$
#1520
0$
#1525
b10111000010100000110100011010100 !
b10111000010100000110100011010100 *
b10010111 -
b1010010111 &
b1010010111 )
b11111111111111111111111010010111 (
b10111000010001100101101111101001 %
b10010110 '
1$
#1530
0$
#1535
b1010011000 &
b1010011000 )
b11111111111111111111111010011000 (
b10111000010100000110100011010100 %
b10010111 '
1$
#1540
0$
#1545
b10111000011001011111011110111101 !
b10111000011001011111011110111101 *
b10011001 -
b1010011001 &
b1010011001 )
b11111111111111111111111010011001 (
b10111000010110101111000001001100 %
b10011000 '
1$
#1550
0$
#1555
b1010011010 &
b1010011010 )
b11111111111111111111111010011010 (
b10111000011001011111011110111101 %
b10011001 '
1$
#1560
0$
#1565
b10111000011111011001110101010001 !
b10111000011111011001110101010001 *
b10011011 -
b1010011011 &
b1010011011 )
b11111111111111111111111010011011 (
b10111000011100011000010011001011 %
b10011010 '
1$
#1570
0$
#1575
b1010011100 &
b1010011100 )
b11111111111111111111111010011100 (
b10111000011111011001110101010001 %
b10011011 '
1$
#1580
0$
#1585
b10111000100010111100010010110111 !
b10111000100010111100010010110111 *
b10011101 -
b1010011101 &
b1010011101 )
b11111111111111111111111010011101 (
b10111000100001010010001110110101 %
b10011100 '
1$
#1590
0$
#1595
b1010011110 &
b1010011110 )
b11111111111111111111111010011110 (
b10111000100010111100010010110111 %
b10011101 '
1$
#1600
0$
